{
	"cmake" : 
	{
		"generator" : 
		{
			"multiConfig" : false,
			"name" : "Ninja"
		},
		"paths" : 
		{
			"cmake" : "F:/FARHAN_NZ/CMake/bin/cmake.exe",
			"cpack" : "F:/FARHAN_NZ/CMake/bin/cpack.exe",
			"ctest" : "F:/FARHAN_NZ/CMake/bin/ctest.exe",
			"root" : "F:/FARHAN_NZ/CMake/share/cmake-3.24"
		},
		"version" : 
		{
			"isDirty" : false,
			"major" : 3,
			"minor" : 24,
			"patch" : 0,
			"string" : "3.24.0-rc3",
			"suffix" : "rc3"
		}
	},
	"objects" : 
	[
		{
			"jsonFile" : "codemodel-v2-09458f160dc6bbae4d5d.json",
			"kind" : "codemodel",
			"version" : 
			{
				"major" : 2,
				"minor" : 4
			}
		},
		{
			"jsonFile" : "cache-v2-4d17cebeb27f68dbe2ad.json",
			"kind" : "cache",
			"version" : 
			{
				"major" : 2,
				"minor" : 0
			}
		},
		{
			"jsonFile" : "cmakeFiles-v1-6433481cc794e0adff93.json",
			"kind" : "cmakeFiles",
			"version" : 
			{
				"major" : 1,
				"minor" : 0
			}
		},
		{
			"jsonFile" : "toolchains-v1-c4cc24c60f32bf55e4a7.json",
			"kind" : "toolchains",
			"version" : 
			{
				"major" : 1,
				"minor" : 0
			}
		}
	],
	"reply" : 
	{
		"client-vscode" : 
		{
			"query.json" : 
			{
				"requests" : 
				[
					{
						"kind" : "cache",
						"version" : 2
					},
					{
						"kind" : "codemodel",
						"version" : 2
					},
					{
						"kind" : "toolchains",
						"version" : 1
					},
					{
						"kind" : "cmakeFiles",
						"version" : 1
					}
				],
				"responses" : 
				[
					{
						"jsonFile" : "cache-v2-4d17cebeb27f68dbe2ad.json",
						"kind" : "cache",
						"version" : 
						{
							"major" : 2,
							"minor" : 0
						}
					},
					{
						"jsonFile" : "codemodel-v2-09458f160dc6bbae4d5d.json",
						"kind" : "codemodel",
						"version" : 
						{
							"major" : 2,
							"minor" : 4
						}
					},
					{
						"jsonFile" : "toolchains-v1-c4cc24c60f32bf55e4a7.json",
						"kind" : "toolchains",
						"version" : 
						{
							"major" : 1,
							"minor" : 0
						}
					},
					{
						"jsonFile" : "cmakeFiles-v1-6433481cc794e0adff93.json",
						"kind" : "cmakeFiles",
						"version" : 
						{
							"major" : 1,
							"minor" : 0
						}
					}
				]
			}
		}
	}
}
